datamaestro_ml/__init__.py
datamaestro_ml/config/edu/uci.py
datamaestro_ml/test/__init__.py
datamaestro_ml/test/test_datasets.py
datamaestro_ml-2021.10.5.dist-info/LICENSE
datamaestro_ml-2021.10.5.dist-info/METADATA
datamaestro_ml-2021.10.5.dist-info/WHEEL
datamaestro_ml-2021.10.5.dist-info/entry_points.txt
datamaestro_ml-2021.10.5.dist-info/top_level.txt
datamaestro_ml-2021.10.5.dist-info/RECORD
