Metadata-Version: 2.1
Name: datamaestro-ml
Version: 2021.10.5
Summary: "Machine learning related datasets"
Home-page: https://github.com/experimaestro/datamaestro_ml
Author: Benjamin Piwowarski
Author-email: benjamin@piwowarski.fr
License: GPL-3
Keywords: dataset manager
Platform: any
Classifier: Development Status :: 4 - Beta
Classifier: Intended Audience :: Science/Research
Classifier: License :: OSI Approved :: GNU General Public License v3 (GPLv3)
Classifier: Operating System :: OS Independent
Classifier: Programming Language :: Python
Classifier: Programming Language :: Python :: 3.5
Classifier: Programming Language :: Python :: 3.6
Classifier: Programming Language :: Python :: 3.7
Classifier: Topic :: Software Development :: Libraries :: Python Modules
Requires-Python: >=3.7
License-File: LICENSE
Requires-Dist: datamaestro (>=0.8)
Provides-Extra: test
Requires-Dist: tox ; extra == 'test'
